openapi_elm_client/__init__.py
openapi_elm_client/cli.py
openapi_elm_client/version.py
openapi_elm_client/generate/__init__.py
openapi_elm_client/generate/common.py
openapi_elm_client/generate/elm_types.py
openapi_elm_client/generate/endpoints.py
openapi_elm_client/generate/function_names.py
openapi_elm_client/generate/json.py
openapi_elm_client/generate/unique_names.py
openapi_elm_client/templates/Client.elm.j2
openapi_elm_client/templates/Gets.elm.j2
openapi_elm_client/templates/Posts.elm.j2
openapi_elm_client/templates/Typedefs.elm.j2
openapi_elm_client-0.3.3.dist-info/LICENSE
openapi_elm_client-0.3.3.dist-info/METADATA
openapi_elm_client-0.3.3.dist-info/WHEEL
openapi_elm_client-0.3.3.dist-info/entry_points.txt
openapi_elm_client-0.3.3.dist-info/top_level.txt
openapi_elm_client-0.3.3.dist-info/RECORD
