Metadata-Version: 2.1
Name: openapi-elm-client
Version: 0.3.3
Summary: Elm client generator for OpenAPI specifications
Home-page: http://github.com/abingham/openapi-elm-client
Author: Austin Bingham
Author-email: austin.bingham@gmail.com
License: MIT
Platform: any
Classifier: Development Status :: 3 - Alpha
Classifier: Operating System :: OS Independent
Classifier: Programming Language :: Python
Classifier: Programming Language :: Python :: 3 :: Only
Requires-Dist: click
Requires-Dist: swagger-to
Provides-Extra: dev
Requires-Dist: black ; extra == 'dev'
Requires-Dist: bumpversion ; extra == 'dev'
Provides-Extra: test
Requires-Dist: godkjenn (<5,>=4) ; extra == 'test'
Requires-Dist: pytest ; extra == 'test'
Requires-Dist: flake8 ; extra == 'test'
